{"code":200,"data":[{"url":"https:\/\/www.9gyou.com\/details\/10111.html","content_id":10111,"title":"穷人捞偏门赚钱最快方法","note":"在中国还是穷人多于富人，身为穷人要想找到赚钱最快的方法其实那么容易？所以，只能靠捞偏门赚钱","img":"..\/images\/6243a6361f98583-220x150.jpg","views":2694,"comment":10,"like":52},{"url":"https:\/\/www.9gyou.com\/details\/10110.html","content_id":10110,"title":"偏门生意门路——看风水赚钱生意","note":"上一篇文章《偏门赚钱项目：生辰八字算命，值得操作！》我们讲的是生辰八字项目，这次，村长讲一","img":"..\/images\/a2e3bc5aaefb5c3-220x150.jpg","views":6765,"comment":5,"like":28},{"url":"https:\/\/www.9gyou.com\/details\/10109.html","content_id":10109,"title":"适合晚上做的偏门生意 一定让你脑洞大开！","note":"偏门生意其实村长讲的很多了，但是，要想把偏门生意发挥到极致还要用一些套路，比如下面村长要说","img":"..\/images\/713deefb89e9656-220x150.jpg","views":3286,"comment":8,"like":66},{"url":"https:\/\/www.9gyou.com\/details\/10108.html","content_id":10108,"title":"穷人捞偏门赚钱门路 走投无路的时候可以试试！","note":"捞偏门赚钱并非有钱人才能做的，也并非需要很多成本，穷人照样可以捞偏门，下面村长介绍几个穷人","img":"..\/images\/ce7f2625c2c6142-220x150.jpg","views":6243,"comment":8,"like":46},{"url":"https:\/\/www.9gyou.com\/details\/10107.html","content_id":10107,"title":"出售假发不为人知的偏门生意（一本万利的生意）","note":"偏门生意其实也会发生在生活中，我们都知道好看的头发不但可以弥补长相的缺陷，更能让你自信满满","img":"..\/images\/ebe6f477ab59862-220x150.jpg","views":5986,"comment":9,"like":65},{"url":"https:\/\/www.9gyou.com\/details\/10106.html","content_id":10106,"title":"捞偏门的赚钱门路 村长有话要说！","note":"本文主要以“捞偏门的赚钱门路”关键词书写的一篇文章，可能不会给你带来偏门项目的介绍，但是，","img":"..\/images\/3786565c689258b-220x150.jpg","views":4727,"comment":7,"like":36},{"url":"https:\/\/www.9gyou.com\/details\/10105.html","content_id":10105,"title":"疫情期间偏门生意：代收代寄快递包裹（月赚几千元）","note":"村长说过偏门生意来源于生活，代收代寄快递包裹大家都听说过，很多人就靠疫情这种特殊时期，月收","img":"..\/images\/d97b431890f765e-220x150.jpg","views":3480,"comment":5,"like":69},{"url":"https:\/\/www.9gyou.com\/details\/10104.html","content_id":10104,"title":"“最”便宜好用的【翻墙VPN软件】可访问谷歌youtube等国外网站","note":"村长说了很多国内的偏门项目了，而国外的偏门项目很少，今天村长就说一个，但是想赚国外的钱，就","img":"..\/images\/3c090260286a85d-220x150.jpg","views":3576,"comment":7,"like":6},{"url":"https:\/\/www.9gyou.com\/details\/10103.html","content_id":10103,"title":"偏门生意：后视镜赚钱 抓住商机就能赚大钱！","note":"我们都知道最近头盔异常爆火，甚至出现买一头盔，难求的局面，其实，头盔火了，自然和它相关的产","img":"..\/images\/9b84edbd96844ed-220x150.jpg","views":7292,"comment":3,"like":90},{"url":"https:\/\/www.9gyou.com\/details\/10102.html","content_id":10102,"title":"偏门生意：反人类”食物，螺蛳粉餐饮项目 有胆量就干吧！","note":"村长说过偏门来源生活，偏门生意也是如此，臭豆腐大家都吃过，但是，螺蛳粉你吃过吗？像屎一样臭","img":"..\/images\/9d16d20926a4d63-220x150.jpg","views":6301,"comment":5,"like":9},{"url":"https:\/\/www.9gyou.com\/details\/10101.html","content_id":10101,"title":"揭秘：有胆量不怕死偏门发财生意，禁止操作！","note":"最近有一人问村长：有胆量不怕死偏门发财生意有没有？当时，村长吓了一跳，心想，这个人受什么刺","img":"..\/images\/bdaa8a8b60fc550-220x150.png","views":4216,"comment":5,"like":69},{"url":"https:\/\/www.9gyou.com\/details\/10100.html","content_id":10100,"title":"2020歪门邪道的赚钱方法","note":"在我们生活中，有些人看似傻啦吧唧，但是，却有一个赚钱的脑子，脑子里有很多歪门邪道的赚钱方法","img":"..\/images\/35afa21d0263c2e-220x150.png","views":5476,"comment":7,"like":13},{"url":"https:\/\/www.9gyou.com\/details\/10099.html","content_id":10099,"title":"偏门生意：产妇排除的胎盘加工成胶囊赚钱!","note":"如果你去过产妇就会看到，经常有很多加工公司，问：“你的胎盘需要加工成胶囊吗？”，我们都知道","img":"..\/images\/ac3bf042a0b3e8b-220x150.jpg","views":1906,"comment":10,"like":42},{"url":"https:\/\/www.9gyou.com\/details\/10098.html","content_id":10098,"title":"现在做什么偏门赚钱？企业老板：2020我只想活着！","note":"网上确实有很多人在咨询：现在做什么偏门赚钱、有什么赚钱的偏门项目吗等问题，但是，你要是线下","img":"..\/images\/9e43f7f4810a14a-220x150.jpg","views":1309,"comment":2,"like":39},{"url":"https:\/\/www.9gyou.com\/details\/10097.html","content_id":10097,"title":"偏门工作推荐：遗体美容师月工资多少？怎么报考遗体美容师？","note":"上一篇文章《偏门工作：火葬场搬尸工 夜班日赚1600，有人一起吗？》提到村长要写一篇遗体美","img":"..\/images\/6679971bc722a95-220x150.jpg","views":5250,"comment":8,"like":51},{"url":"https:\/\/www.9gyou.com\/details\/10096.html","content_id":10096,"title":"偏门生意：刷脸支付项目，有人脉，后期躺着赚钱！","note":"刷脸支付也属于偏门生意，因为它是风口项目，2019年下半年才火起来的项目，所以，比较偏门，","img":"..\/images\/5b15bd9885432c8-220x150.jpg","views":3501,"comment":10,"like":57},{"url":"https:\/\/www.9gyou.com\/details\/10095.html","content_id":10095,"title":"偏门生意：王者荣耀S20初赛季代练上分赚钱 月入万元不是梦！","note":"村长说一个自疫情以后，比较火的偏门赚钱生意，那就是王者荣耀代练，举个例子，如果你是白金1想","img":"..\/images\/b1cfba1620118ad-220x150.jpg","views":7585,"comment":3,"like":66},{"url":"https:\/\/www.9gyou.com\/details\/10094.html","content_id":10094,"title":"偏门生意:揭秘高端男士养生会所是如何套路男人的！","note":"偏门生意千千万，选择一个坚持干，下面这个偏门生意你应该感兴趣，那就是高端男士养生会所，据村","img":"..\/images\/4633fce9702e915-220x150.jpg","views":5031,"comment":10,"like":74},{"url":"https:\/\/www.9gyou.com\/details\/10093.html","content_id":10093,"title":"做别人想不到的生意，赚别人赚不了的钱，收入比上班工资高多了！","note":"上班是很难赚到钱，做生意又找不到好的项目，其实，那是因为你走了别人的老路，所以赚不到钱，要","img":"..\/images\/e5b7429536f5b29-220x150.jpg","views":5872,"comment":4,"like":31},{"url":"https:\/\/www.9gyou.com\/details\/10092.html","content_id":10092,"title":"揭秘：假房东套路真租客，暴利骗钱，年入百万元（禁止操作）！","note":"大部分租客都是上班族，找一个合适的房子确实不容易，但是别贪便宜，因为容易上当受骗，最近，村","img":"..\/images\/c896afff957f491-220x150.jpg","views":6170,"comment":8,"like":92}],"next":true}